porter/__init__.py
porter/api.py
porter/config.py
porter/constants.py
porter/datascience.py
porter/exceptions.py
porter/loading.py
porter/responses.py
porter/services.py
porter/utils.py
porter/assets/swagger-ui/README.md
porter/assets/swagger-ui/favicon-16x16.png
porter/assets/swagger-ui/favicon-32x32.png
porter/assets/swagger-ui/index.html
porter/assets/swagger-ui/oauth2-redirect.html
porter/assets/swagger-ui/swagger-ui-bundle.js
porter/assets/swagger-ui/swagger-ui-bundle.js.map
porter/assets/swagger-ui/swagger-ui-standalone-preset.js
porter/assets/swagger-ui/swagger-ui-standalone-preset.js.map
porter/assets/swagger-ui/swagger-ui.css
porter/assets/swagger-ui/swagger-ui.css.map
porter/assets/swagger-ui/swagger-ui.js
porter/assets/swagger-ui/swagger-ui.js.map
porter/assets/swagger-ui/swagger_template.html
porter/schemas/__init__.py
porter/schemas/openapi.py
porter/schemas/schemas.py
porter_apis-0.16.0.dist-info/LICENSE
porter_apis-0.16.0.dist-info/METADATA
porter_apis-0.16.0.dist-info/WHEEL
porter_apis-0.16.0.dist-info/top_level.txt
porter_apis-0.16.0.dist-info/RECORD
