Metadata-Version: 2.1
Name: porter-apis
Version: 0.16.0
Summary: porter is a framework for exposing machine learning models via REST APIs.
Author-email: Dante Gates <dantedgates@gmail.com>
Project-URL: Homepage, https://github.com/dantegates/porter
Project-URL: Bug Tracker, https://github.com/dantegates/porter/issues
Classifier: Programming Language :: Python :: 3
Classifier: License :: OSI Approved :: MIT License
Classifier: Operating System :: OS Independent
Requires-Python: >=3.9.0
License-File: LICENSE
Requires-Dist: Flask <4.0.0,>=3.0.0
Requires-Dist: numpy >=1.24.0
Requires-Dist: pandas >=2.0.0
Requires-Dist: joblib >=1.3.0
Requires-Dist: fastjsonschema >=2.18.0
Provides-Extra: all
Requires-Dist: tensorflow >=2.13.0 ; extra == 'all'
Requires-Dist: scikit-learn >=1.3.0 ; extra == 'all'
Provides-Extra: keras-utils
Requires-Dist: tensorflow >=2.13.0 ; extra == 'keras-utils'
Provides-Extra: sklearn-utils
Requires-Dist: scikit-learn >=1.3.0 ; extra == 'sklearn-utils'
